.gitignore
AUTHORS
BUGS
COPYING
INSTALL
MANIFEST.in
SUGGESTIONS
setup.cfg
setup.py
examples/metagui.py
examples/test_dictionaries.py
examples/test_libs.py
examples/triplets_app.py
pgpu/__init__.py
pgpu/compatibility.py
pgpu/dictionaries.py
pgpu/encoding.py
pgpu/file_utils.py
pgpu/iter_utils.py
pgpu/math_utils.py
pgpu/string_utils.py
pgpu/time_widgets.py
pgpu/tk_utils.py
pgpu/wrappers.py
pgpu.egg-info/PKG-INFO
pgpu.egg-info/SOURCES.txt
pgpu.egg-info/dependency_links.txt
pgpu.egg-info/pbr.json
pgpu.egg-info/top_level.txt
pgpu/tkinter2x/__init__.py
pgpu/tkinter2x/canvas.py
pgpu/tkinter2x/colorchooser.py
pgpu/tkinter2x/constants.py
pgpu/tkinter2x/dialog.py
pgpu/tkinter2x/dnd.py
pgpu/tkinter2x/filedialog.py
pgpu/tkinter2x/font.py
pgpu/tkinter2x/messagebox.py
pgpu/tkinter2x/scrolledtext.py
pgpu/tkinter2x/simpledialog.py
pgpu/tkinter2x/tix.py
pgpu/tkinter2x/ttk.py