Metadata-Version: 1.1
Name: pgpu
Version: 2.0.0
Summary: Pydsigner's Generic Python Utilities (PGPU) -- a collection of handy modules and packages for Python.
Home-page: http://github.com/pydsigner/PGPU
Author: Daniel Foerster/pydsigner
Author-email: pydsigner@gmail.com
License: LGPLv3
Platform: UNKNOWN
Classifier: Development Status :: 5 - Production/Stable
Classifier: Intended Audience :: Developers
Classifier: Operating System :: MacOS :: MacOS X
Classifier: Operating System :: Microsoft :: Windows
Classifier: Operating System :: POSIX
Classifier: Programming Language :: Python
